{
  "info": {
    "_postman_id": "lms-simple-collection",
    "name": "LMS-Simple API",
    "description": "Library Management System API Collection",
    "schema": "https://schema.getpostman.com/json/collection/v2.1.0/collection.json"
  },
  "variable": [
    {
      "key": "baseUrl",
      "value": "http://localhost:3000",
      "type": "string"
    },
    {
      "key": "token",
      "value": "",
      "type": "string"
    }
  ],
  "item": [
    {
      "name": "Health",
      "item": [
        {
          "name": "Health Check",
          "request": {
            "method": "GET",
            "header": [],
            "url": {
              "raw": "{{baseUrl}}/health",
              "host": ["{{baseUrl}}"],
              "path": ["health"]
            }
          }
        }
      ]
    },
    {
      "name": "Auth",
      "item": [
        {
          "name": "Register User",
          "request": {
            "method": "POST",
            "header": [
              {
                "key": "Content-Type",
                "value": "application/json"
              }
            ],
            "body": {
              "mode": "raw",
              "raw": "{\n  \"email\": \"newuser@lms.test\",\n  \"password\": \"Test@12345\",\n  \"full_name\": \"New User\",\n  \"role\": \"MEMBER\"\n}"
            },
            "url": {
              "raw": "{{baseUrl}}/auth/register",
              "host": ["{{baseUrl}}"],
              "path": ["auth", "register"]
            }
          }
        },
        {
          "name": "Login (Admin)",
          "event": [
            {
              "listen": "test",
              "script": {
                "exec": [
                  "var jsonData = pm.response.json();",
                  "if (jsonData.token) {",
                  "    pm.collectionVariables.set('token', jsonData.token);",
                  "}"
                ],
                "type": "text/javascript"
              }
            }
          ],
          "request": {
            "method": "POST",
            "header": [
              {
                "key": "Content-Type",
                "value": "application/json"
              }
            ],
            "body": {
              "mode": "raw",
              "raw": "{\n  \"email\": \"admin@lms.test\",\n  \"password\": \"Admin@123\"\n}"
            },
            "url": {
              "raw": "{{baseUrl}}/auth/login",
              "host": ["{{baseUrl}}"],
              "path": ["auth", "login"]
            }
          }
        },
        {
          "name": "Login (Librarian)",
          "event": [
            {
              "listen": "test",
              "script": {
                "exec": [
                  "var jsonData = pm.response.json();",
                  "if (jsonData.token) {",
                  "    pm.collectionVariables.set('token', jsonData.token);",
                  "}"
                ],
                "type": "text/javascript"
              }
            }
          ],
          "request": {
            "method": "POST",
            "header": [
              {
                "key": "Content-Type",
                "value": "application/json"
              }
            ],
            "body": {
              "mode": "raw",
              "raw": "{\n  \"email\": \"lib@lms.test\",\n  \"password\": \"Lib@12345\"\n}"
            },
            "url": {
              "raw": "{{baseUrl}}/auth/login",
              "host": ["{{baseUrl}}"],
              "path": ["auth", "login"]
            }
          }
        },
        {
          "name": "Login (Member)",
          "event": [
            {
              "listen": "test",
              "script": {
                "exec": [
                  "var jsonData = pm.response.json();",
                  "if (jsonData.token) {",
                  "    pm.collectionVariables.set('token', jsonData.token);",
                  "}"
                ],
                "type": "text/javascript"
              }
            }
          ],
          "request": {
            "method": "POST",
            "header": [
              {
                "key": "Content-Type",
                "value": "application/json"
              }
            ],
            "body": {
              "mode": "raw",
              "raw": "{\n  \"email\": \"mem@lms.test\",\n  \"password\": \"Mem@12345\"\n}"
            },
            "url": {
              "raw": "{{baseUrl}}/auth/login",
              "host": ["{{baseUrl}}"],
              "path": ["auth", "login"]
            }
          }
        }
      ]
    },
    {
      "name": "Books",
      "item": [
        {
          "name": "List All Books",
          "request": {
            "method": "GET",
            "header": [
              {
                "key": "Authorization",
                "value": "Bearer {{token}}"
              }
            ],
            "url": {
              "raw": "{{baseUrl}}/books",
              "host": ["{{baseUrl}}"],
              "path": ["books"]
            }
          }
        },
        {
          "name": "Search Books",
          "request": {
            "method": "GET",
            "header": [
              {
                "key": "Authorization",
                "value": "Bearer {{token}}"
              }
            ],
            "url": {
              "raw": "{{baseUrl}}/books?q=programming",
              "host": ["{{baseUrl}}"],
              "path": ["books"],
              "query": [
                {
                  "key": "q",
                  "value": "programming"
                }
              ]
            }
          }
        },
        {
          "name": "Get Book by ID",
          "request": {
            "method": "GET",
            "header": [
              {
                "key": "Authorization",
                "value": "Bearer {{token}}"
              }
            ],
            "url": {
              "raw": "{{baseUrl}}/books/1",
              "host": ["{{baseUrl}}"],
              "path": ["books", "1"]
            }
          }
        },
        {
          "name": "Create Book",
          "request": {
            "method": "POST",
            "header": [
              {
                "key": "Authorization",
                "value": "Bearer {{token}}"
              },
              {
                "key": "Content-Type",
                "value": "application/json"
              }
            ],
            "body": {
              "mode": "raw",
              "raw": "{\n  \"isbn\": \"978-0-000-00000-0\",\n  \"title\": \"New Book Title\",\n  \"author\": \"Author Name\",\n  \"description\": \"A great book about something interesting.\",\n  \"categories\": \"Programming, Web Development\",\n  \"total_copies\": 3\n}"
            },
            "url": {
              "raw": "{{baseUrl}}/books",
              "host": ["{{baseUrl}}"],
              "path": ["books"]
            }
          }
        },
        {
          "name": "Update Book",
          "request": {
            "method": "PATCH",
            "header": [
              {
                "key": "Authorization",
                "value": "Bearer {{token}}"
              },
              {
                "key": "Content-Type",
                "value": "application/json"
              }
            ],
            "body": {
              "mode": "raw",
              "raw": "{\n  \"title\": \"Updated Book Title\",\n  \"total_copies\": 5\n}"
            },
            "url": {
              "raw": "{{baseUrl}}/books/1",
              "host": ["{{baseUrl}}"],
              "path": ["books", "1"]
            }
          }
        },
        {
          "name": "Delete Book",
          "request": {
            "method": "DELETE",
            "header": [
              {
                "key": "Authorization",
                "value": "Bearer {{token}}"
              }
            ],
            "url": {
              "raw": "{{baseUrl}}/books/1",
              "host": ["{{baseUrl}}"],
              "path": ["books", "1"]
            }
          }
        }
      ]
    },
    {
      "name": "Loans",
      "item": [
        {
          "name": "List Loans",
          "request": {
            "method": "GET",
            "header": [
              {
                "key": "Authorization",
                "value": "Bearer {{token}}"
              }
            ],
            "url": {
              "raw": "{{baseUrl}}/loans",
              "host": ["{{baseUrl}}"],
              "path": ["loans"]
            }
          }
        },
        {
          "name": "List Loans (Filtered)",
          "request": {
            "method": "GET",
            "header": [
              {
                "key": "Authorization",
                "value": "Bearer {{token}}"
              }
            ],
            "url": {
              "raw": "{{baseUrl}}/loans?status=ISSUED",
              "host": ["{{baseUrl}}"],
              "path": ["loans"],
              "query": [
                {
                  "key": "status",
                  "value": "ISSUED"
                }
              ]
            }
          }
        },
        {
          "name": "Issue Book",
          "request": {
            "method": "POST",
            "header": [
              {
                "key": "Authorization",
                "value": "Bearer {{token}}"
              },
              {
                "key": "Content-Type",
                "value": "application/json"
              }
            ],
            "body": {
              "mode": "raw",
              "raw": "{\n  \"user_id\": 3,\n  \"book_id\": 1\n}"
            },
            "url": {
              "raw": "{{baseUrl}}/loans/issue",
              "host": ["{{baseUrl}}"],
              "path": ["loans", "issue"]
            }
          }
        },
        {
          "name": "Return Book",
          "request": {
            "method": "POST",
            "header": [
              {
                "key": "Authorization",
                "value": "Bearer {{token}}"
              },
              {
                "key": "Content-Type",
                "value": "application/json"
              }
            ],
            "body": {
              "mode": "raw",
              "raw": "{\n  \"loan_id\": 1\n}"
            },
            "url": {
              "raw": "{{baseUrl}}/loans/return",
              "host": ["{{baseUrl}}"],
              "path": ["loans", "return"]
            }
          }
        },
        {
          "name": "Renew Loan",
          "request": {
            "method": "POST",
            "header": [
              {
                "key": "Authorization",
                "value": "Bearer {{token}}"
              },
              {
                "key": "Content-Type",
                "value": "application/json"
              }
            ],
            "body": {
              "mode": "raw",
              "raw": "{\n  \"loan_id\": 1\n}"
            },
            "url": {
              "raw": "{{baseUrl}}/loans/renew",
              "host": ["{{baseUrl}}"],
              "path": ["loans", "renew"]
            }
          }
        }
      ]
    },
    {
      "name": "Reservations",
      "item": [
        {
          "name": "List Reservations",
          "request": {
            "method": "GET",
            "header": [
              {
                "key": "Authorization",
                "value": "Bearer {{token}}"
              }
            ],
            "url": {
              "raw": "{{baseUrl}}/reservations",
              "host": ["{{baseUrl}}"],
              "path": ["reservations"]
            }
          }
        },
        {
          "name": "Create Reservation",
          "request": {
            "method": "POST",
            "header": [
              {
                "key": "Authorization",
                "value": "Bearer {{token}}"
              },
              {
                "key": "Content-Type",
                "value": "application/json"
              }
            ],
            "body": {
              "mode": "raw",
              "raw": "{\n  \"user_id\": 3,\n  \"book_id\": 2\n}"
            },
            "url": {
              "raw": "{{baseUrl}}/reservations",
              "host": ["{{baseUrl}}"],
              "path": ["reservations"]
            }
          }
        },
        {
          "name": "Cancel Reservation",
          "request": {
            "method": "POST",
            "header": [
              {
                "key": "Authorization",
                "value": "Bearer {{token}}"
              }
            ],
            "url": {
              "raw": "{{baseUrl}}/reservations/1/cancel",
              "host": ["{{baseUrl}}"],
              "path": ["reservations", "1", "cancel"]
            }
          }
        }
      ]
    },
    {
      "name": "Search",
      "item": [
        {
          "name": "Semantic Search",
          "request": {
            "method": "POST",
            "header": [
              {
                "key": "Authorization",
                "value": "Bearer {{token}}"
              },
              {
                "key": "Content-Type",
                "value": "application/json"
              }
            ],
            "body": {
              "mode": "raw",
              "raw": "{\n  \"query\": \"programming best practices\",\n  \"limit\": 5\n}"
            },
            "url": {
              "raw": "{{baseUrl}}/search/semantic",
              "host": ["{{baseUrl}}"],
              "path": ["search", "semantic"]
            }
          }
        },
        {
          "name": "Auto-Suggest",
          "request": {
            "method": "GET",
            "header": [
              {
                "key": "Authorization",
                "value": "Bearer {{token}}"
              }
            ],
            "url": {
              "raw": "{{baseUrl}}/search/suggest?prefix=The",
              "host": ["{{baseUrl}}"],
              "path": ["search", "suggest"],
              "query": [
                {
                  "key": "prefix",
                  "value": "The"
                }
              ]
            }
          }
        }
      ]
    },
    {
      "name": "Recommendations",
      "item": [
        {
          "name": "User Recommendations",
          "request": {
            "method": "GET",
            "header": [
              {
                "key": "Authorization",
                "value": "Bearer {{token}}"
              }
            ],
            "url": {
              "raw": "{{baseUrl}}/recommendations/user/3",
              "host": ["{{baseUrl}}"],
              "path": ["recommendations", "user", "3"]
            }
          }
        },
        {
          "name": "Similar Books",
          "request": {
            "method": "GET",
            "header": [
              {
                "key": "Authorization",
                "value": "Bearer {{token}}"
              }
            ],
            "url": {
              "raw": "{{baseUrl}}/recommendations/similar/1",
              "host": ["{{baseUrl}}"],
              "path": ["recommendations", "similar", "1"]
            }
          }
        }
      ]
    },
    {
      "name": "Inventory",
      "item": [
        {
          "name": "Low Stock",
          "request": {
            "method": "GET",
            "header": [
              {
                "key": "Authorization",
                "value": "Bearer {{token}}"
              }
            ],
            "url": {
              "raw": "{{baseUrl}}/inventory/low-stock?threshold=3",
              "host": ["{{baseUrl}}"],
              "path": ["inventory", "low-stock"],
              "query": [
                {
                  "key": "threshold",
                  "value": "3"
                }
              ]
            }
          }
        }
      ]
    },
    {
      "name": "Notifications",
      "item": [
        {
          "name": "Send Due Reminders",
          "request": {
            "method": "POST",
            "header": [
              {
                "key": "Authorization",
                "value": "Bearer {{token}}"
              }
            ],
            "url": {
              "raw": "{{baseUrl}}/notifications/send-due-reminders",
              "host": ["{{baseUrl}}"],
              "path": ["notifications", "send-due-reminders"]
            }
          }
        }
      ]
    }
  ]
}
